LICENSE.txt
MANIFEST.in
NEWS.txt
README.rst
setup.py
src/django_merlin.egg-info/PKG-INFO
src/django_merlin.egg-info/SOURCES.txt
src/django_merlin.egg-info/dependency_links.txt
src/django_merlin.egg-info/not-zip-safe
src/django_merlin.egg-info/top_level.txt
src/merlin/__init__.py
src/merlin/tests/__init__.py
src/merlin/tests/test_session_wizard.py
src/merlin/tests/test_utils.py
src/merlin/tests/fixtures/__init__.py
src/merlin/tests/fixtures/testproject/__init__.py
src/merlin/tests/fixtures/testproject/forms.py
src/merlin/tests/fixtures/testproject/manage.py
src/merlin/tests/fixtures/testproject/settings.py
src/merlin/tests/fixtures/testproject/urls.py
src/merlin/tests/fixtures/testproject/views.py
src/merlin/tests/fixtures/testproject/wizard.py
src/merlin/wizards/__init__.py
src/merlin/wizards/session.py
src/merlin/wizards/utils.py