Metadata-Version: 1.0
Name: django-merlin
Version: 0.8
Summary: Providing alternate form wizards for the Django project.
Home-page: http://github.com/supercodepoet/django-merlin
Author: supercodepoet
Author-email: travis@travischase.me
License: BSD
Keywords: forms wizard django session
Platform: UNKNOWN
Classifier: Development Status :: 4 - Beta
Classifier: Framework :: Django
Classifier: Intended Audience :: Developers
Classifier: License :: OSI Approved :: BSD License
Classifier: Natural Language :: English
Classifier: Programming Language :: Python :: 2.7
